[
    {
        "r_name": "Room #0",
        "r_id": 0,
        "stud_count": 9
    },
    {
        "r_name": "Room #1",
        "r_id": 1,
        "stud_count": 7
    },
    {
        "r_name": "Room #10",
        "r_id": 10,
        "stud_count": 13
    },
    {
        "r_name": "Room #100",
        "r_id": 100,
        "stud_count": 9
    },
    {
        "r_name": "Room #101",
        "r_id": 101,
        "stud_count": 10
    },
    {
        "r_name": "Room #102",
        "r_id": 102,
        "stud_count": 5
    },
    {
        "r_name": "Room #103",
        "r_id": 103,
        "stud_count": 12
    },
    {
        "r_name": "Room #104",
        "r_id": 104,
        "stud_count": 12
    },
    {
        "r_name": "Room #105",
        "r_id": 105,
        "stud_count": 5
    },
    {
        "r_name": "Room #106",
        "r_id": 106,
        "stud_count": 9
    },
    {
        "r_name": "Room #107",
        "r_id": 107,
        "stud_count": 12
    },
    {
        "r_name": "Room #108",
        "r_id": 108,
        "stud_count": 10
    },
    {
        "r_name": "Room #109",
        "r_id": 109,
        "stud_count": 7
    },
    {
        "r_name": "Room #11",
        "r_id": 11,
        "stud_count": 12
    },
    {
        "r_name": "Room #110",
        "r_id": 110,
        "stud_count": 9
    },
    {
        "r_name": "Room #111",
        "r_id": 111,
        "stud_count": 10
    },
    {
        "r_name": "Room #112",
        "r_id": 112,
        "stud_count": 11
    },
    {
        "r_name": "Room #113",
        "r_id": 113,
        "stud_count": 9
    },
    {
        "r_name": "Room #114",
        "r_id": 114,
        "stud_count": 11
    },
    {
        "r_name": "Room #115",
        "r_id": 115,
        "stud_count": 9
    },
    {
        "r_name": "Room #116",
        "r_id": 116,
        "stud_count": 14
    },
    {
        "r_name": "Room #117",
        "r_id": 117,
        "stud_count": 12
    },
    {
        "r_name": "Room #118",
        "r_id": 118,
        "stud_count": 10
    },
    {
        "r_name": "Room #119",
        "r_id": 119,
        "stud_count": 8
    },
    {
        "r_name": "Room #12",
        "r_id": 12,
        "stud_count": 16
    },
    {
        "r_name": "Room #120",
        "r_id": 120,
        "stud_count": 12
    },
    {
        "r_name": "Room #121",
        "r_id": 121,
        "stud_count": 10
    },
    {
        "r_name": "Room #122",
        "r_id": 122,
        "stud_count": 10
    },
    {
        "r_name": "Room #123",
        "r_id": 123,
        "stud_count": 12
    },
    {
        "r_name": "Room #124",
        "r_id": 124,
        "stud_count": 14
    },
    {
        "r_name": "Room #125",
        "r_id": 125,
        "stud_count": 8
    },
    {
        "r_name": "Room #126",
        "r_id": 126,
        "stud_count": 11
    },
    {
        "r_name": "Room #127",
        "r_id": 127,
        "stud_count": 11
    },
    {
        "r_name": "Room #128",
        "r_id": 128,
        "stud_count": 13
    },
    {
        "r_name": "Room #129",
        "r_id": 129,
        "stud_count": 8
    },
    {
        "r_name": "Room #13",
        "r_id": 13,
        "stud_count": 10
    },
    {
        "r_name": "Room #130",
        "r_id": 130,
        "stud_count": 10
    },
    {
        "r_name": "Room #131",
        "r_id": 131,
        "stud_count": 8
    },
    {
        "r_name": "Room #132",
        "r_id": 132,
        "stud_count": 11
    },
    {
        "r_name": "Room #133",
        "r_id": 133,
        "stud_count": 16
    },
    {
        "r_name": "Room #134",
        "r_id": 134,
        "stud_count": 4
    },
    {
        "r_name": "Room #135",
        "r_id": 135,
        "stud_count": 7
    },
    {
        "r_name": "Room #136",
        "r_id": 136,
        "stud_count": 16
    },
    {
        "r_name": "Room #137",
        "r_id": 137,
        "stud_count": 11
    },
    {
        "r_name": "Room #138",
        "r_id": 138,
        "stud_count": 13
    },
    {
        "r_name": "Room #139",
        "r_id": 139,
        "stud_count": 14
    },
    {
        "r_name": "Room #14",
        "r_id": 14,
        "stud_count": 7
    },
    {
        "r_name": "Room #140",
        "r_id": 140,
        "stud_count": 5
    },
    {
        "r_name": "Room #141",
        "r_id": 141,
        "stud_count": 5
    },
    {
        "r_name": "Room #142",
        "r_id": 142,
        "stud_count": 11
    },
    {
        "r_name": "Room #143",
        "r_id": 143,
        "stud_count": 10
    },
    {
        "r_name": "Room #144",
        "r_id": 144,
        "stud_count": 11
    },
    {
        "r_name": "Room #145",
        "r_id": 145,
        "stud_count": 16
    },
    {
        "r_name": "Room #146",
        "r_id": 146,
        "stud_count": 12
    },
    {
        "r_name": "Room #147",
        "r_id": 147,
        "stud_count": 8
    },
    {
        "r_name": "Room #148",
        "r_id": 148,
        "stud_count": 7
    },
    {
        "r_name": "Room #149",
        "r_id": 149,
        "stud_count": 11
    },
    {
        "r_name": "Room #15",
        "r_id": 15,
        "stud_count": 9
    },
    {
        "r_name": "Room #150",
        "r_id": 150,
        "stud_count": 6
    },
    {
        "r_name": "Room #151",
        "r_id": 151,
        "stud_count": 12
    },
    {
        "r_name": "Room #152",
        "r_id": 152,
        "stud_count": 6
    },
    {
        "r_name": "Room #153",
        "r_id": 153,
        "stud_count": 7
    },
    {
        "r_name": "Room #154",
        "r_id": 154,
        "stud_count": 3
    },
    {
        "r_name": "Room #155",
        "r_id": 155,
        "stud_count": 18
    },
    {
        "r_name": "Room #156",
        "r_id": 156,
        "stud_count": 9
    },
    {
        "r_name": "Room #157",
        "r_id": 157,
        "stud_count": 4
    },
    {
        "r_name": "Room #158",
        "r_id": 158,
        "stud_count": 7
    },
    {
        "r_name": "Room #159",
        "r_id": 159,
        "stud_count": 7
    },
    {
        "r_name": "Room #16",
        "r_id": 16,
        "stud_count": 10
    },
    {
        "r_name": "Room #160",
        "r_id": 160,
        "stud_count": 10
    },
    {
        "r_name": "Room #161",
        "r_id": 161,
        "stud_count": 15
    },
    {
        "r_name": "Room #162",
        "r_id": 162,
        "stud_count": 10
    },
    {
        "r_name": "Room #163",
        "r_id": 163,
        "stud_count": 8
    },
    {
        "r_name": "Room #164",
        "r_id": 164,
        "stud_count": 8
    },
    {
        "r_name": "Room #165",
        "r_id": 165,
        "stud_count": 10
    },
    {
        "r_name": "Room #166",
        "r_id": 166,
        "stud_count": 9
    },
    {
        "r_name": "Room #167",
        "r_id": 167,
        "stud_count": 7
    },
    {
        "r_name": "Room #168",
        "r_id": 168,
        "stud_count": 7
    },
    {
        "r_name": "Room #169",
        "r_id": 169,
        "stud_count": 14
    },
    {
        "r_name": "Room #17",
        "r_id": 17,
        "stud_count": 9
    },
    {
        "r_name": "Room #170",
        "r_id": 170,
        "stud_count": 7
    },
    {
        "r_name": "Room #171",
        "r_id": 171,
        "stud_count": 6
    },
    {
        "r_name": "Room #172",
        "r_id": 172,
        "stud_count": 10
    },
    {
        "r_name": "Room #173",
        "r_id": 173,
        "stud_count": 10
    },
    {
        "r_name": "Room #174",
        "r_id": 174,
        "stud_count": 11
    },
    {
        "r_name": "Room #175",
        "r_id": 175,
        "stud_count": 13
    },
    {
        "r_name": "Room #176",
        "r_id": 176,
        "stud_count": 12
    },
    {
        "r_name": "Room #177",
        "r_id": 177,
        "stud_count": 6
    },
    {
        "r_name": "Room #178",
        "r_id": 178,
        "stud_count": 4
    },
    {
        "r_name": "Room #179",
        "r_id": 179,
        "stud_count": 10
    },
    {
        "r_name": "Room #18",
        "r_id": 18,
        "stud_count": 10
    },
    {
        "r_name": "Room #180",
        "r_id": 180,
        "stud_count": 8
    },
    {
        "r_name": "Room #181",
        "r_id": 181,
        "stud_count": 7
    },
    {
        "r_name": "Room #182",
        "r_id": 182,
        "stud_count": 6
    },
    {
        "r_name": "Room #183",
        "r_id": 183,
        "stud_count": 7
    },
    {
        "r_name": "Room #184",
        "r_id": 184,
        "stud_count": 6
    },
    {
        "r_name": "Room #185",
        "r_id": 185,
        "stud_count": 8
    },
    {
        "r_name": "Room #186",
        "r_id": 186,
        "stud_count": 6
    },
    {
        "r_name": "Room #187",
        "r_id": 187,
        "stud_count": 14
    },
    {
        "r_name": "Room #188",
        "r_id": 188,
        "stud_count": 12
    },
    {
        "r_name": "Room #189",
        "r_id": 189,
        "stud_count": 12
    },
    {
        "r_name": "Room #19",
        "r_id": 19,
        "stud_count": 13
    },
    {
        "r_name": "Room #190",
        "r_id": 190,
        "stud_count": 9
    },
    {
        "r_name": "Room #191",
        "r_id": 191,
        "stud_count": 7
    },
    {
        "r_name": "Room #192",
        "r_id": 192,
        "stud_count": 8
    },
    {
        "r_name": "Room #193",
        "r_id": 193,
        "stud_count": 11
    },
    {
        "r_name": "Room #194",
        "r_id": 194,
        "stud_count": 8
    },
    {
        "r_name": "Room #195",
        "r_id": 195,
        "stud_count": 14
    },
    {
        "r_name": "Room #196",
        "r_id": 196,
        "stud_count": 13
    },
    {
        "r_name": "Room #197",
        "r_id": 197,
        "stud_count": 19
    },
    {
        "r_name": "Room #198",
        "r_id": 198,
        "stud_count": 13
    },
    {
        "r_name": "Room #199",
        "r_id": 199,
        "stud_count": 12
    },
    {
        "r_name": "Room #2",
        "r_id": 2,
        "stud_count": 9
    },
    {
        "r_name": "Room #20",
        "r_id": 20,
        "stud_count": 15
    },
    {
        "r_name": "Room #200",
        "r_id": 200,
        "stud_count": 15
    },
    {
        "r_name": "Room #201",
        "r_id": 201,
        "stud_count": 13
    },
    {
        "r_name": "Room #202",
        "r_id": 202,
        "stud_count": 8
    },
    {
        "r_name": "Room #203",
        "r_id": 203,
        "stud_count": 9
    },
    {
        "r_name": "Room #204",
        "r_id": 204,
        "stud_count": 9
    },
    {
        "r_name": "Room #205",
        "r_id": 205,
        "stud_count": 16
    },
    {
        "r_name": "Room #206",
        "r_id": 206,
        "stud_count": 6
    },
    {
        "r_name": "Room #207",
        "r_id": 207,
        "stud_count": 11
    },
    {
        "r_name": "Room #208",
        "r_id": 208,
        "stud_count": 10
    },
    {
        "r_name": "Room #209",
        "r_id": 209,
        "stud_count": 16
    },
    {
        "r_name": "Room #21",
        "r_id": 21,
        "stud_count": 15
    },
    {
        "r_name": "Room #210",
        "r_id": 210,
        "stud_count": 9
    },
    {
        "r_name": "Room #211",
        "r_id": 211,
        "stud_count": 9
    },
    {
        "r_name": "Room #212",
        "r_id": 212,
        "stud_count": 8
    },
    {
        "r_name": "Room #213",
        "r_id": 213,
        "stud_count": 12
    },
    {
        "r_name": "Room #214",
        "r_id": 214,
        "stud_count": 14
    },
    {
        "r_name": "Room #215",
        "r_id": 215,
        "stud_count": 10
    },
    {
        "r_name": "Room #216",
        "r_id": 216,
        "stud_count": 6
    },
    {
        "r_name": "Room #217",
        "r_id": 217,
        "stud_count": 14
    },
    {
        "r_name": "Room #218",
        "r_id": 218,
        "stud_count": 8
    },
    {
        "r_name": "Room #219",
        "r_id": 219,
        "stud_count": 6
    },
    {
        "r_name": "Room #22",
        "r_id": 22,
        "stud_count": 9
    },
    {
        "r_name": "Room #220",
        "r_id": 220,
        "stud_count": 10
    },
    {
        "r_name": "Room #221",
        "r_id": 221,
        "stud_count": 12
    },
    {
        "r_name": "Room #222",
        "r_id": 222,
        "stud_count": 9
    },
    {
        "r_name": "Room #223",
        "r_id": 223,
        "stud_count": 6
    },
    {
        "r_name": "Room #224",
        "r_id": 224,
        "stud_count": 7
    },
    {
        "r_name": "Room #225",
        "r_id": 225,
        "stud_count": 14
    },
    {
        "r_name": "Room #226",
        "r_id": 226,
        "stud_count": 8
    },
    {
        "r_name": "Room #227",
        "r_id": 227,
        "stud_count": 11
    },
    {
        "r_name": "Room #228",
        "r_id": 228,
        "stud_count": 9
    },
    {
        "r_name": "Room #229",
        "r_id": 229,
        "stud_count": 7
    },
    {
        "r_name": "Room #23",
        "r_id": 23,
        "stud_count": 16
    },
    {
        "r_name": "Room #230",
        "r_id": 230,
        "stud_count": 10
    },
    {
        "r_name": "Room #231",
        "r_id": 231,
        "stud_count": 11
    },
    {
        "r_name": "Room #232",
        "r_id": 232,
        "stud_count": 8
    },
    {
        "r_name": "Room #233",
        "r_id": 233,
        "stud_count": 11
    },
    {
        "r_name": "Room #234",
        "r_id": 234,
        "stud_count": 11
    },
    {
        "r_name": "Room #235",
        "r_id": 235,
        "stud_count": 11
    },
    {
        "r_name": "Room #236",
        "r_id": 236,
        "stud_count": 10
    },
    {
        "r_name": "Room #237",
        "r_id": 237,
        "stud_count": 16
    },
    {
        "r_name": "Room #238",
        "r_id": 238,
        "stud_count": 12
    },
    {
        "r_name": "Room #239",
        "r_id": 239,
        "stud_count": 10
    },
    {
        "r_name": "Room #24",
        "r_id": 24,
        "stud_count": 14
    },
    {
        "r_name": "Room #240",
        "r_id": 240,
        "stud_count": 12
    },
    {
        "r_name": "Room #241",
        "r_id": 241,
        "stud_count": 10
    },
    {
        "r_name": "Room #242",
        "r_id": 242,
        "stud_count": 13
    },
    {
        "r_name": "Room #243",
        "r_id": 243,
        "stud_count": 9
    },
    {
        "r_name": "Room #244",
        "r_id": 244,
        "stud_count": 10
    },
    {
        "r_name": "Room #245",
        "r_id": 245,
        "stud_count": 10
    },
    {
        "r_name": "Room #246",
        "r_id": 246,
        "stud_count": 5
    },
    {
        "r_name": "Room #247",
        "r_id": 247,
        "stud_count": 12
    },
    {
        "r_name": "Room #248",
        "r_id": 248,
        "stud_count": 8
    },
    {
        "r_name": "Room #249",
        "r_id": 249,
        "stud_count": 12
    },
    {
        "r_name": "Room #25",
        "r_id": 25,
        "stud_count": 4
    },
    {
        "r_name": "Room #250",
        "r_id": 250,
        "stud_count": 12
    },
    {
        "r_name": "Room #251",
        "r_id": 251,
        "stud_count": 8
    },
    {
        "r_name": "Room #252",
        "r_id": 252,
        "stud_count": 11
    },
    {
        "r_name": "Room #253",
        "r_id": 253,
        "stud_count": 13
    },
    {
        "r_name": "Room #254",
        "r_id": 254,
        "stud_count": 8
    },
    {
        "r_name": "Room #255",
        "r_id": 255,
        "stud_count": 6
    },
    {
        "r_name": "Room #256",
        "r_id": 256,
        "stud_count": 11
    },
    {
        "r_name": "Room #257",
        "r_id": 257,
        "stud_count": 8
    },
    {
        "r_name": "Room #258",
        "r_id": 258,
        "stud_count": 8
    },
    {
        "r_name": "Room #259",
        "r_id": 259,
        "stud_count": 14
    },
    {
        "r_name": "Room #26",
        "r_id": 26,
        "stud_count": 7
    },
    {
        "r_name": "Room #260",
        "r_id": 260,
        "stud_count": 12
    },
    {
        "r_name": "Room #261",
        "r_id": 261,
        "stud_count": 7
    },
    {
        "r_name": "Room #262",
        "r_id": 262,
        "stud_count": 8
    },
    {
        "r_name": "Room #263",
        "r_id": 263,
        "stud_count": 9
    },
    {
        "r_name": "Room #264",
        "r_id": 264,
        "stud_count": 7
    },
    {
        "r_name": "Room #265",
        "r_id": 265,
        "stud_count": 14
    },
    {
        "r_name": "Room #266",
        "r_id": 266,
        "stud_count": 13
    },
    {
        "r_name": "Room #267",
        "r_id": 267,
        "stud_count": 7
    },
    {
        "r_name": "Room #268",
        "r_id": 268,
        "stud_count": 15
    },
    {
        "r_name": "Room #269",
        "r_id": 269,
        "stud_count": 10
    },
    {
        "r_name": "Room #27",
        "r_id": 27,
        "stud_count": 6
    },
    {
        "r_name": "Room #270",
        "r_id": 270,
        "stud_count": 10
    },
    {
        "r_name": "Room #271",
        "r_id": 271,
        "stud_count": 11
    },
    {
        "r_name": "Room #272",
        "r_id": 272,
        "stud_count": 8
    },
    {
        "r_name": "Room #273",
        "r_id": 273,
        "stud_count": 9
    },
    {
        "r_name": "Room #274",
        "r_id": 274,
        "stud_count": 10
    },
    {
        "r_name": "Room #275",
        "r_id": 275,
        "stud_count": 12
    },
    {
        "r_name": "Room #276",
        "r_id": 276,
        "stud_count": 10
    },
    {
        "r_name": "Room #277",
        "r_id": 277,
        "stud_count": 10
    },
    {
        "r_name": "Room #278",
        "r_id": 278,
        "stud_count": 9
    },
    {
        "r_name": "Room #279",
        "r_id": 279,
        "stud_count": 10
    },
    {
        "r_name": "Room #28",
        "r_id": 28,
        "stud_count": 7
    },
    {
        "r_name": "Room #280",
        "r_id": 280,
        "stud_count": 11
    },
    {
        "r_name": "Room #281",
        "r_id": 281,
        "stud_count": 8
    },
    {
        "r_name": "Room #282",
        "r_id": 282,
        "stud_count": 10
    },
    {
        "r_name": "Room #283",
        "r_id": 283,
        "stud_count": 7
    },
    {
        "r_name": "Room #284",
        "r_id": 284,
        "stud_count": 11
    },
    {
        "r_name": "Room #285",
        "r_id": 285,
        "stud_count": 10
    },
    {
        "r_name": "Room #286",
        "r_id": 286,
        "stud_count": 6
    },
    {
        "r_name": "Room #287",
        "r_id": 287,
        "stud_count": 12
    },
    {
        "r_name": "Room #288",
        "r_id": 288,
        "stud_count": 9
    },
    {
        "r_name": "Room #289",
        "r_id": 289,
        "stud_count": 15
    },
    {
        "r_name": "Room #29",
        "r_id": 29,
        "stud_count": 12
    },
    {
        "r_name": "Room #290",
        "r_id": 290,
        "stud_count": 9
    },
    {
        "r_name": "Room #291",
        "r_id": 291,
        "stud_count": 10
    },
    {
        "r_name": "Room #292",
        "r_id": 292,
        "stud_count": 10
    },
    {
        "r_name": "Room #293",
        "r_id": 293,
        "stud_count": 12
    },
    {
        "r_name": "Room #294",
        "r_id": 294,
        "stud_count": 11
    },
    {
        "r_name": "Room #295",
        "r_id": 295,
        "stud_count": 8
    },
    {
        "r_name": "Room #296",
        "r_id": 296,
        "stud_count": 8
    },
    {
        "r_name": "Room #297",
        "r_id": 297,
        "stud_count": 13
    },
    {
        "r_name": "Room #298",
        "r_id": 298,
        "stud_count": 9
    },
    {
        "r_name": "Room #299",
        "r_id": 299,
        "stud_count": 8
    },
    {
        "r_name": "Room #3",
        "r_id": 3,
        "stud_count": 5
    },
    {
        "r_name": "Room #30",
        "r_id": 30,
        "stud_count": 9
    },
    {
        "r_name": "Room #300",
        "r_id": 300,
        "stud_count": 12
    },
    {
        "r_name": "Room #301",
        "r_id": 301,
        "stud_count": 10
    },
    {
        "r_name": "Room #302",
        "r_id": 302,
        "stud_count": 8
    },
    {
        "r_name": "Room #303",
        "r_id": 303,
        "stud_count": 9
    },
    {
        "r_name": "Room #304",
        "r_id": 304,
        "stud_count": 11
    },
    {
        "r_name": "Room #305",
        "r_id": 305,
        "stud_count": 14
    },
    {
        "r_name": "Room #306",
        "r_id": 306,
        "stud_count": 10
    },
    {
        "r_name": "Room #307",
        "r_id": 307,
        "stud_count": 10
    },
    {
        "r_name": "Room #308",
        "r_id": 308,
        "stud_count": 10
    },
    {
        "r_name": "Room #309",
        "r_id": 309,
        "stud_count": 7
    },
    {
        "r_name": "Room #31",
        "r_id": 31,
        "stud_count": 13
    },
    {
        "r_name": "Room #310",
        "r_id": 310,
        "stud_count": 10
    },
    {
        "r_name": "Room #311",
        "r_id": 311,
        "stud_count": 14
    },
    {
        "r_name": "Room #312",
        "r_id": 312,
        "stud_count": 11
    },
    {
        "r_name": "Room #313",
        "r_id": 313,
        "stud_count": 8
    },
    {
        "r_name": "Room #314",
        "r_id": 314,
        "stud_count": 11
    },
    {
        "r_name": "Room #315",
        "r_id": 315,
        "stud_count": 10
    },
    {
        "r_name": "Room #316",
        "r_id": 316,
        "stud_count": 11
    },
    {
        "r_name": "Room #317",
        "r_id": 317,
        "stud_count": 14
    },
    {
        "r_name": "Room #318",
        "r_id": 318,
        "stud_count": 15
    },
    {
        "r_name": "Room #319",
        "r_id": 319,
        "stud_count": 11
    },
    {
        "r_name": "Room #32",
        "r_id": 32,
        "stud_count": 9
    },
    {
        "r_name": "Room #320",
        "r_id": 320,
        "stud_count": 7
    },
    {
        "r_name": "Room #321",
        "r_id": 321,
        "stud_count": 13
    },
    {
        "r_name": "Room #322",
        "r_id": 322,
        "stud_count": 9
    },
    {
        "r_name": "Room #323",
        "r_id": 323,
        "stud_count": 13
    },
    {
        "r_name": "Room #324",
        "r_id": 324,
        "stud_count": 6
    },
    {
        "r_name": "Room #325",
        "r_id": 325,
        "stud_count": 6
    },
    {
        "r_name": "Room #326",
        "r_id": 326,
        "stud_count": 18
    },
    {
        "r_name": "Room #327",
        "r_id": 327,
        "stud_count": 8
    },
    {
        "r_name": "Room #328",
        "r_id": 328,
        "stud_count": 16
    },
    {
        "r_name": "Room #329",
        "r_id": 329,
        "stud_count": 10
    },
    {
        "r_name": "Room #33",
        "r_id": 33,
        "stud_count": 9
    },
    {
        "r_name": "Room #330",
        "r_id": 330,
        "stud_count": 11
    },
    {
        "r_name": "Room #331",
        "r_id": 331,
        "stud_count": 12
    },
    {
        "r_name": "Room #332",
        "r_id": 332,
        "stud_count": 11
    },
    {
        "r_name": "Room #333",
        "r_id": 333,
        "stud_count": 5
    },
    {
        "r_name": "Room #334",
        "r_id": 334,
        "stud_count": 10
    },
    {
        "r_name": "Room #335",
        "r_id": 335,
        "stud_count": 8
    },
    {
        "r_name": "Room #336",
        "r_id": 336,
        "stud_count": 11
    },
    {
        "r_name": "Room #337",
        "r_id": 337,
        "stud_count": 11
    },
    {
        "r_name": "Room #338",
        "r_id": 338,
        "stud_count": 11
    },
    {
        "r_name": "Room #339",
        "r_id": 339,
        "stud_count": 8
    },
    {
        "r_name": "Room #34",
        "r_id": 34,
        "stud_count": 9
    },
    {
        "r_name": "Room #340",
        "r_id": 340,
        "stud_count": 7
    },
    {
        "r_name": "Room #341",
        "r_id": 341,
        "stud_count": 9
    },
    {
        "r_name": "Room #342",
        "r_id": 342,
        "stud_count": 14
    },
    {
        "r_name": "Room #343",
        "r_id": 343,
        "stud_count": 14
    },
    {
        "r_name": "Room #344",
        "r_id": 344,
        "stud_count": 13
    },
    {
        "r_name": "Room #345",
        "r_id": 345,
        "stud_count": 4
    },
    {
        "r_name": "Room #346",
        "r_id": 346,
        "stud_count": 10
    },
    {
        "r_name": "Room #347",
        "r_id": 347,
        "stud_count": 12
    },
    {
        "r_name": "Room #348",
        "r_id": 348,
        "stud_count": 12
    },
    {
        "r_name": "Room #349",
        "r_id": 349,
        "stud_count": 8
    },
    {
        "r_name": "Room #35",
        "r_id": 35,
        "stud_count": 14
    },
    {
        "r_name": "Room #350",
        "r_id": 350,
        "stud_count": 11
    },
    {
        "r_name": "Room #351",
        "r_id": 351,
        "stud_count": 6
    },
    {
        "r_name": "Room #352",
        "r_id": 352,
        "stud_count": 8
    },
    {
        "r_name": "Room #353",
        "r_id": 353,
        "stud_count": 4
    },
    {
        "r_name": "Room #354",
        "r_id": 354,
        "stud_count": 6
    },
    {
        "r_name": "Room #355",
        "r_id": 355,
        "stud_count": 16
    },
    {
        "r_name": "Room #356",
        "r_id": 356,
        "stud_count": 16
    },
    {
        "r_name": "Room #357",
        "r_id": 357,
        "stud_count": 16
    },
    {
        "r_name": "Room #358",
        "r_id": 358,
        "stud_count": 11
    },
    {
        "r_name": "Room #359",
        "r_id": 359,
        "stud_count": 18
    },
    {
        "r_name": "Room #36",
        "r_id": 36,
        "stud_count": 10
    },
    {
        "r_name": "Room #360",
        "r_id": 360,
        "stud_count": 8
    },
    {
        "r_name": "Room #361",
        "r_id": 361,
        "stud_count": 6
    },
    {
        "r_name": "Room #362",
        "r_id": 362,
        "stud_count": 10
    },
    {
        "r_name": "Room #363",
        "r_id": 363,
        "stud_count": 7
    },
    {
        "r_name": "Room #364",
        "r_id": 364,
        "stud_count": 8
    },
    {
        "r_name": "Room #365",
        "r_id": 365,
        "stud_count": 14
    },
    {
        "r_name": "Room #366",
        "r_id": 366,
        "stud_count": 15
    },
    {
        "r_name": "Room #367",
        "r_id": 367,
        "stud_count": 11
    },
    {
        "r_name": "Room #368",
        "r_id": 368,
        "stud_count": 13
    },
    {
        "r_name": "Room #369",
        "r_id": 369,
        "stud_count": 13
    },
    {
        "r_name": "Room #37",
        "r_id": 37,
        "stud_count": 12
    },
    {
        "r_name": "Room #370",
        "r_id": 370,
        "stud_count": 10
    },
    {
        "r_name": "Room #371",
        "r_id": 371,
        "stud_count": 14
    },
    {
        "r_name": "Room #372",
        "r_id": 372,
        "stud_count": 7
    },
    {
        "r_name": "Room #373",
        "r_id": 373,
        "stud_count": 16
    },
    {
        "r_name": "Room #374",
        "r_id": 374,
        "stud_count": 9
    },
    {
        "r_name": "Room #375",
        "r_id": 375,
        "stud_count": 8
    },
    {
        "r_name": "Room #376",
        "r_id": 376,
        "stud_count": 11
    },
    {
        "r_name": "Room #377",
        "r_id": 377,
        "stud_count": 8
    },
    {
        "r_name": "Room #378",
        "r_id": 378,
        "stud_count": 11
    },
    {
        "r_name": "Room #379",
        "r_id": 379,
        "stud_count": 12
    },
    {
        "r_name": "Room #38",
        "r_id": 38,
        "stud_count": 10
    },
    {
        "r_name": "Room #380",
        "r_id": 380,
        "stud_count": 8
    },
    {
        "r_name": "Room #381",
        "r_id": 381,
        "stud_count": 11
    },
    {
        "r_name": "Room #382",
        "r_id": 382,
        "stud_count": 5
    },
    {
        "r_name": "Room #383",
        "r_id": 383,
        "stud_count": 5
    },
    {
        "r_name": "Room #384",
        "r_id": 384,
        "stud_count": 7
    },
    {
        "r_name": "Room #385",
        "r_id": 385,
        "stud_count": 11
    },
    {
        "r_name": "Room #386",
        "r_id": 386,
        "stud_count": 11
    },
    {
        "r_name": "Room #387",
        "r_id": 387,
        "stud_count": 10
    },
    {
        "r_name": "Room #388",
        "r_id": 388,
        "stud_count": 9
    },
    {
        "r_name": "Room #389",
        "r_id": 389,
        "stud_count": 9
    },
    {
        "r_name": "Room #39",
        "r_id": 39,
        "stud_count": 12
    },
    {
        "r_name": "Room #390",
        "r_id": 390,
        "stud_count": 15
    },
    {
        "r_name": "Room #391",
        "r_id": 391,
        "stud_count": 10
    },
    {
        "r_name": "Room #392",
        "r_id": 392,
        "stud_count": 18
    },
    {
        "r_name": "Room #393",
        "r_id": 393,
        "stud_count": 8
    },
    {
        "r_name": "Room #394",
        "r_id": 394,
        "stud_count": 9
    },
    {
        "r_name": "Room #395",
        "r_id": 395,
        "stud_count": 13
    },
    {
        "r_name": "Room #396",
        "r_id": 396,
        "stud_count": 5
    },
    {
        "r_name": "Room #397",
        "r_id": 397,
        "stud_count": 8
    },
    {
        "r_name": "Room #398",
        "r_id": 398,
        "stud_count": 13
    },
    {
        "r_name": "Room #399",
        "r_id": 399,
        "stud_count": 9
    },
    {
        "r_name": "Room #4",
        "r_id": 4,
        "stud_count": 11
    },
    {
        "r_name": "Room #40",
        "r_id": 40,
        "stud_count": 11
    },
    {
        "r_name": "Room #400",
        "r_id": 400,
        "stud_count": 11
    },
    {
        "r_name": "Room #401",
        "r_id": 401,
        "stud_count": 7
    },
    {
        "r_name": "Room #402",
        "r_id": 402,
        "stud_count": 10
    },
    {
        "r_name": "Room #403",
        "r_id": 403,
        "stud_count": 6
    },
    {
        "r_name": "Room #404",
        "r_id": 404,
        "stud_count": 7
    },
    {
        "r_name": "Room #405",
        "r_id": 405,
        "stud_count": 7
    },
    {
        "r_name": "Room #406",
        "r_id": 406,
        "stud_count": 14
    },
    {
        "r_name": "Room #407",
        "r_id": 407,
        "stud_count": 10
    },
    {
        "r_name": "Room #408",
        "r_id": 408,
        "stud_count": 9
    },
    {
        "r_name": "Room #409",
        "r_id": 409,
        "stud_count": 8
    },
    {
        "r_name": "Room #41",
        "r_id": 41,
        "stud_count": 15
    },
    {
        "r_name": "Room #410",
        "r_id": 410,
        "stud_count": 6
    },
    {
        "r_name": "Room #411",
        "r_id": 411,
        "stud_count": 9
    },
    {
        "r_name": "Room #412",
        "r_id": 412,
        "stud_count": 13
    },
    {
        "r_name": "Room #413",
        "r_id": 413,
        "stud_count": 9
    },
    {
        "r_name": "Room #414",
        "r_id": 414,
        "stud_count": 10
    },
    {
        "r_name": "Room #415",
        "r_id": 415,
        "stud_count": 12
    },
    {
        "r_name": "Room #416",
        "r_id": 416,
        "stud_count": 8
    },
    {
        "r_name": "Room #417",
        "r_id": 417,
        "stud_count": 9
    },
    {
        "r_name": "Room #418",
        "r_id": 418,
        "stud_count": 15
    },
    {
        "r_name": "Room #419",
        "r_id": 419,
        "stud_count": 3
    },
    {
        "r_name": "Room #42",
        "r_id": 42,
        "stud_count": 8
    },
    {
        "r_name": "Room #420",
        "r_id": 420,
        "stud_count": 6
    },
    {
        "r_name": "Room #421",
        "r_id": 421,
        "stud_count": 9
    },
    {
        "r_name": "Room #422",
        "r_id": 422,
        "stud_count": 2
    },
    {
        "r_name": "Room #423",
        "r_id": 423,
        "stud_count": 16
    },
    {
        "r_name": "Room #424",
        "r_id": 424,
        "stud_count": 8
    },
    {
        "r_name": "Room #425",
        "r_id": 425,
        "stud_count": 9
    },
    {
        "r_name": "Room #426",
        "r_id": 426,
        "stud_count": 10
    },
    {
        "r_name": "Room #427",
        "r_id": 427,
        "stud_count": 8
    },
    {
        "r_name": "Room #428",
        "r_id": 428,
        "stud_count": 10
    },
    {
        "r_name": "Room #429",
        "r_id": 429,
        "stud_count": 10
    },
    {
        "r_name": "Room #43",
        "r_id": 43,
        "stud_count": 9
    },
    {
        "r_name": "Room #430",
        "r_id": 430,
        "stud_count": 9
    },
    {
        "r_name": "Room #431",
        "r_id": 431,
        "stud_count": 11
    },
    {
        "r_name": "Room #432",
        "r_id": 432,
        "stud_count": 15
    },
    {
        "r_name": "Room #433",
        "r_id": 433,
        "stud_count": 9
    },
    {
        "r_name": "Room #434",
        "r_id": 434,
        "stud_count": 9
    },
    {
        "r_name": "Room #435",
        "r_id": 435,
        "stud_count": 11
    },
    {
        "r_name": "Room #436",
        "r_id": 436,
        "stud_count": 5
    },
    {
        "r_name": "Room #437",
        "r_id": 437,
        "stud_count": 16
    },
    {
        "r_name": "Room #438",
        "r_id": 438,
        "stud_count": 11
    },
    {
        "r_name": "Room #439",
        "r_id": 439,
        "stud_count": 11
    },
    {
        "r_name": "Room #44",
        "r_id": 44,
        "stud_count": 16
    },
    {
        "r_name": "Room #440",
        "r_id": 440,
        "stud_count": 6
    },
    {
        "r_name": "Room #441",
        "r_id": 441,
        "stud_count": 7
    },
    {
        "r_name": "Room #442",
        "r_id": 442,
        "stud_count": 15
    },
    {
        "r_name": "Room #443",
        "r_id": 443,
        "stud_count": 4
    },
    {
        "r_name": "Room #444",
        "r_id": 444,
        "stud_count": 8
    },
    {
        "r_name": "Room #445",
        "r_id": 445,
        "stud_count": 8
    },
    {
        "r_name": "Room #446",
        "r_id": 446,
        "stud_count": 11
    },
    {
        "r_name": "Room #447",
        "r_id": 447,
        "stud_count": 14
    },
    {
        "r_name": "Room #448",
        "r_id": 448,
        "stud_count": 18
    },
    {
        "r_name": "Room #449",
        "r_id": 449,
        "stud_count": 8
    },
    {
        "r_name": "Room #45",
        "r_id": 45,
        "stud_count": 10
    },
    {
        "r_name": "Room #450",
        "r_id": 450,
        "stud_count": 6
    },
    {
        "r_name": "Room #451",
        "r_id": 451,
        "stud_count": 15
    },
    {
        "r_name": "Room #452",
        "r_id": 452,
        "stud_count": 14
    },
    {
        "r_name": "Room #453",
        "r_id": 453,
        "stud_count": 10
    },
    {
        "r_name": "Room #454",
        "r_id": 454,
        "stud_count": 9
    },
    {
        "r_name": "Room #455",
        "r_id": 455,
        "stud_count": 10
    },
    {
        "r_name": "Room #456",
        "r_id": 456,
        "stud_count": 6
    },
    {
        "r_name": "Room #457",
        "r_id": 457,
        "stud_count": 13
    },
    {
        "r_name": "Room #458",
        "r_id": 458,
        "stud_count": 9
    },
    {
        "r_name": "Room #459",
        "r_id": 459,
        "stud_count": 11
    },
    {
        "r_name": "Room #46",
        "r_id": 46,
        "stud_count": 12
    },
    {
        "r_name": "Room #460",
        "r_id": 460,
        "stud_count": 14
    },
    {
        "r_name": "Room #461",
        "r_id": 461,
        "stud_count": 8
    },
    {
        "r_name": "Room #462",
        "r_id": 462,
        "stud_count": 8
    },
    {
        "r_name": "Room #463",
        "r_id": 463,
        "stud_count": 11
    },
    {
        "r_name": "Room #464",
        "r_id": 464,
        "stud_count": 16
    },
    {
        "r_name": "Room #465",
        "r_id": 465,
        "stud_count": 11
    },
    {
        "r_name": "Room #466",
        "r_id": 466,
        "stud_count": 5
    },
    {
        "r_name": "Room #467",
        "r_id": 467,
        "stud_count": 11
    },
    {
        "r_name": "Room #468",
        "r_id": 468,
        "stud_count": 11
    },
    {
        "r_name": "Room #469",
        "r_id": 469,
        "stud_count": 15
    },
    {
        "r_name": "Room #47",
        "r_id": 47,
        "stud_count": 9
    },
    {
        "r_name": "Room #470",
        "r_id": 470,
        "stud_count": 8
    },
    {
        "r_name": "Room #471",
        "r_id": 471,
        "stud_count": 10
    },
    {
        "r_name": "Room #472",
        "r_id": 472,
        "stud_count": 8
    },
    {
        "r_name": "Room #473",
        "r_id": 473,
        "stud_count": 14
    },
    {
        "r_name": "Room #474",
        "r_id": 474,
        "stud_count": 9
    },
    {
        "r_name": "Room #475",
        "r_id": 475,
        "stud_count": 9
    },
    {
        "r_name": "Room #476",
        "r_id": 476,
        "stud_count": 9
    },
    {
        "r_name": "Room #477",
        "r_id": 477,
        "stud_count": 10
    },
    {
        "r_name": "Room #478",
        "r_id": 478,
        "stud_count": 6
    },
    {
        "r_name": "Room #479",
        "r_id": 479,
        "stud_count": 6
    },
    {
        "r_name": "Room #48",
        "r_id": 48,
        "stud_count": 12
    },
    {
        "r_name": "Room #480",
        "r_id": 480,
        "stud_count": 6
    },
    {
        "r_name": "Room #481",
        "r_id": 481,
        "stud_count": 9
    },
    {
        "r_name": "Room #483",
        "r_id": 483,
        "stud_count": 10
    },
    {
        "r_name": "Room #484",
        "r_id": 484,
        "stud_count": 4
    },
    {
        "r_name": "Room #485",
        "r_id": 485,
        "stud_count": 7
    },
    {
        "r_name": "Room #486",
        "r_id": 486,
        "stud_count": 17
    },
    {
        "r_name": "Room #487",
        "r_id": 487,
        "stud_count": 4
    },
    {
        "r_name": "Room #488",
        "r_id": 488,
        "stud_count": 15
    },
    {
        "r_name": "Room #489",
        "r_id": 489,
        "stud_count": 17
    },
    {
        "r_name": "Room #49",
        "r_id": 49,
        "stud_count": 3
    },
    {
        "r_name": "Room #490",
        "r_id": 490,
        "stud_count": 11
    },
    {
        "r_name": "Room #491",
        "r_id": 491,
        "stud_count": 17
    },
    {
        "r_name": "Room #492",
        "r_id": 492,
        "stud_count": 8
    },
    {
        "r_name": "Room #493",
        "r_id": 493,
        "stud_count": 7
    },
    {
        "r_name": "Room #494",
        "r_id": 494,
        "stud_count": 6
    },
    {
        "r_name": "Room #495",
        "r_id": 495,
        "stud_count": 6
    },
    {
        "r_name": "Room #496",
        "r_id": 496,
        "stud_count": 12
    },
    {
        "r_name": "Room #497",
        "r_id": 497,
        "stud_count": 17
    },
    {
        "r_name": "Room #498",
        "r_id": 498,
        "stud_count": 4
    },
    {
        "r_name": "Room #499",
        "r_id": 499,
        "stud_count": 8
    },
    {
        "r_name": "Room #5",
        "r_id": 5,
        "stud_count": 9
    },
    {
        "r_name": "Room #50",
        "r_id": 50,
        "stud_count": 6
    },
    {
        "r_name": "Room #500",
        "r_id": 500,
        "stud_count": 10
    },
    {
        "r_name": "Room #501",
        "r_id": 501,
        "stud_count": 10
    },
    {
        "r_name": "Room #502",
        "r_id": 502,
        "stud_count": 8
    },
    {
        "r_name": "Room #503",
        "r_id": 503,
        "stud_count": 10
    },
    {
        "r_name": "Room #504",
        "r_id": 504,
        "stud_count": 10
    },
    {
        "r_name": "Room #505",
        "r_id": 505,
        "stud_count": 15
    },
    {
        "r_name": "Room #506",
        "r_id": 506,
        "stud_count": 18
    },
    {
        "r_name": "Room #507",
        "r_id": 507,
        "stud_count": 9
    },
    {
        "r_name": "Room #508",
        "r_id": 508,
        "stud_count": 9
    },
    {
        "r_name": "Room #509",
        "r_id": 509,
        "stud_count": 12
    },
    {
        "r_name": "Room #51",
        "r_id": 51,
        "stud_count": 15
    },
    {
        "r_name": "Room #510",
        "r_id": 510,
        "stud_count": 14
    },
    {
        "r_name": "Room #511",
        "r_id": 511,
        "stud_count": 10
    },
    {
        "r_name": "Room #512",
        "r_id": 512,
        "stud_count": 9
    },
    {
        "r_name": "Room #513",
        "r_id": 513,
        "stud_count": 12
    },
    {
        "r_name": "Room #514",
        "r_id": 514,
        "stud_count": 15
    },
    {
        "r_name": "Room #515",
        "r_id": 515,
        "stud_count": 10
    },
    {
        "r_name": "Room #516",
        "r_id": 516,
        "stud_count": 13
    },
    {
        "r_name": "Room #517",
        "r_id": 517,
        "stud_count": 9
    },
    {
        "r_name": "Room #518",
        "r_id": 518,
        "stud_count": 11
    },
    {
        "r_name": "Room #519",
        "r_id": 519,
        "stud_count": 12
    },
    {
        "r_name": "Room #52",
        "r_id": 52,
        "stud_count": 15
    },
    {
        "r_name": "Room #520",
        "r_id": 520,
        "stud_count": 13
    },
    {
        "r_name": "Room #521",
        "r_id": 521,
        "stud_count": 16
    },
    {
        "r_name": "Room #522",
        "r_id": 522,
        "stud_count": 5
    },
    {
        "r_name": "Room #523",
        "r_id": 523,
        "stud_count": 11
    },
    {
        "r_name": "Room #524",
        "r_id": 524,
        "stud_count": 8
    },
    {
        "r_name": "Room #525",
        "r_id": 525,
        "stud_count": 14
    },
    {
        "r_name": "Room #526",
        "r_id": 526,
        "stud_count": 10
    },
    {
        "r_name": "Room #527",
        "r_id": 527,
        "stud_count": 13
    },
    {
        "r_name": "Room #528",
        "r_id": 528,
        "stud_count": 11
    },
    {
        "r_name": "Room #529",
        "r_id": 529,
        "stud_count": 9
    },
    {
        "r_name": "Room #53",
        "r_id": 53,
        "stud_count": 9
    },
    {
        "r_name": "Room #530",
        "r_id": 530,
        "stud_count": 14
    },
    {
        "r_name": "Room #531",
        "r_id": 531,
        "stud_count": 8
    },
    {
        "r_name": "Room #532",
        "r_id": 532,
        "stud_count": 12
    },
    {
        "r_name": "Room #533",
        "r_id": 533,
        "stud_count": 10
    },
    {
        "r_name": "Room #534",
        "r_id": 534,
        "stud_count": 14
    },
    {
        "r_name": "Room #535",
        "r_id": 535,
        "stud_count": 15
    },
    {
        "r_name": "Room #536",
        "r_id": 536,
        "stud_count": 10
    },
    {
        "r_name": "Room #537",
        "r_id": 537,
        "stud_count": 13
    },
    {
        "r_name": "Room #538",
        "r_id": 538,
        "stud_count": 5
    },
    {
        "r_name": "Room #539",
        "r_id": 539,
        "stud_count": 8
    },
    {
        "r_name": "Room #54",
        "r_id": 54,
        "stud_count": 6
    },
    {
        "r_name": "Room #540",
        "r_id": 540,
        "stud_count": 5
    },
    {
        "r_name": "Room #541",
        "r_id": 541,
        "stud_count": 15
    },
    {
        "r_name": "Room #542",
        "r_id": 542,
        "stud_count": 9
    },
    {
        "r_name": "Room #543",
        "r_id": 543,
        "stud_count": 14
    },
    {
        "r_name": "Room #544",
        "r_id": 544,
        "stud_count": 13
    },
    {
        "r_name": "Room #545",
        "r_id": 545,
        "stud_count": 12
    },
    {
        "r_name": "Room #546",
        "r_id": 546,
        "stud_count": 10
    },
    {
        "r_name": "Room #547",
        "r_id": 547,
        "stud_count": 13
    },
    {
        "r_name": "Room #548",
        "r_id": 548,
        "stud_count": 11
    },
    {
        "r_name": "Room #549",
        "r_id": 549,
        "stud_count": 8
    },
    {
        "r_name": "Room #55",
        "r_id": 55,
        "stud_count": 9
    },
    {
        "r_name": "Room #550",
        "r_id": 550,
        "stud_count": 15
    },
    {
        "r_name": "Room #551",
        "r_id": 551,
        "stud_count": 8
    },
    {
        "r_name": "Room #552",
        "r_id": 552,
        "stud_count": 11
    },
    {
        "r_name": "Room #553",
        "r_id": 553,
        "stud_count": 13
    },
    {
        "r_name": "Room #554",
        "r_id": 554,
        "stud_count": 7
    },
    {
        "r_name": "Room #555",
        "r_id": 555,
        "stud_count": 8
    },
    {
        "r_name": "Room #556",
        "r_id": 556,
        "stud_count": 17
    },
    {
        "r_name": "Room #557",
        "r_id": 557,
        "stud_count": 14
    },
    {
        "r_name": "Room #558",
        "r_id": 558,
        "stud_count": 7
    },
    {
        "r_name": "Room #559",
        "r_id": 559,
        "stud_count": 14
    },
    {
        "r_name": "Room #56",
        "r_id": 56,
        "stud_count": 13
    },
    {
        "r_name": "Room #560",
        "r_id": 560,
        "stud_count": 10
    },
    {
        "r_name": "Room #561",
        "r_id": 561,
        "stud_count": 13
    },
    {
        "r_name": "Room #562",
        "r_id": 562,
        "stud_count": 9
    },
    {
        "r_name": "Room #563",
        "r_id": 563,
        "stud_count": 16
    },
    {
        "r_name": "Room #564",
        "r_id": 564,
        "stud_count": 7
    },
    {
        "r_name": "Room #565",
        "r_id": 565,
        "stud_count": 9
    },
    {
        "r_name": "Room #566",
        "r_id": 566,
        "stud_count": 9
    },
    {
        "r_name": "Room #567",
        "r_id": 567,
        "stud_count": 10
    },
    {
        "r_name": "Room #568",
        "r_id": 568,
        "stud_count": 7
    },
    {
        "r_name": "Room #569",
        "r_id": 569,
        "stud_count": 6
    },
    {
        "r_name": "Room #57",
        "r_id": 57,
        "stud_count": 9
    },
    {
        "r_name": "Room #570",
        "r_id": 570,
        "stud_count": 11
    },
    {
        "r_name": "Room #571",
        "r_id": 571,
        "stud_count": 5
    },
    {
        "r_name": "Room #572",
        "r_id": 572,
        "stud_count": 14
    },
    {
        "r_name": "Room #573",
        "r_id": 573,
        "stud_count": 17
    },
    {
        "r_name": "Room #574",
        "r_id": 574,
        "stud_count": 10
    },
    {
        "r_name": "Room #575",
        "r_id": 575,
        "stud_count": 12
    },
    {
        "r_name": "Room #576",
        "r_id": 576,
        "stud_count": 10
    },
    {
        "r_name": "Room #577",
        "r_id": 577,
        "stud_count": 8
    },
    {
        "r_name": "Room #578",
        "r_id": 578,
        "stud_count": 6
    },
    {
        "r_name": "Room #579",
        "r_id": 579,
        "stud_count": 7
    },
    {
        "r_name": "Room #58",
        "r_id": 58,
        "stud_count": 12
    },
    {
        "r_name": "Room #580",
        "r_id": 580,
        "stud_count": 7
    },
    {
        "r_name": "Room #581",
        "r_id": 581,
        "stud_count": 13
    },
    {
        "r_name": "Room #582",
        "r_id": 582,
        "stud_count": 13
    },
    {
        "r_name": "Room #583",
        "r_id": 583,
        "stud_count": 9
    },
    {
        "r_name": "Room #584",
        "r_id": 584,
        "stud_count": 11
    },
    {
        "r_name": "Room #585",
        "r_id": 585,
        "stud_count": 7
    },
    {
        "r_name": "Room #586",
        "r_id": 586,
        "stud_count": 8
    },
    {
        "r_name": "Room #587",
        "r_id": 587,
        "stud_count": 9
    },
    {
        "r_name": "Room #588",
        "r_id": 588,
        "stud_count": 12
    },
    {
        "r_name": "Room #589",
        "r_id": 589,
        "stud_count": 7
    },
    {
        "r_name": "Room #59",
        "r_id": 59,
        "stud_count": 9
    },
    {
        "r_name": "Room #590",
        "r_id": 590,
        "stud_count": 12
    },
    {
        "r_name": "Room #591",
        "r_id": 591,
        "stud_count": 18
    },
    {
        "r_name": "Room #592",
        "r_id": 592,
        "stud_count": 11
    },
    {
        "r_name": "Room #593",
        "r_id": 593,
        "stud_count": 8
    },
    {
        "r_name": "Room #594",
        "r_id": 594,
        "stud_count": 11
    },
    {
        "r_name": "Room #595",
        "r_id": 595,
        "stud_count": 7
    },
    {
        "r_name": "Room #596",
        "r_id": 596,
        "stud_count": 9
    },
    {
        "r_name": "Room #597",
        "r_id": 597,
        "stud_count": 13
    },
    {
        "r_name": "Room #598",
        "r_id": 598,
        "stud_count": 9
    },
    {
        "r_name": "Room #599",
        "r_id": 599,
        "stud_count": 16
    },
    {
        "r_name": "Room #6",
        "r_id": 6,
        "stud_count": 4
    },
    {
        "r_name": "Room #60",
        "r_id": 60,
        "stud_count": 9
    },
    {
        "r_name": "Room #600",
        "r_id": 600,
        "stud_count": 7
    },
    {
        "r_name": "Room #601",
        "r_id": 601,
        "stud_count": 11
    },
    {
        "r_name": "Room #602",
        "r_id": 602,
        "stud_count": 10
    },
    {
        "r_name": "Room #603",
        "r_id": 603,
        "stud_count": 13
    },
    {
        "r_name": "Room #604",
        "r_id": 604,
        "stud_count": 8
    },
    {
        "r_name": "Room #605",
        "r_id": 605,
        "stud_count": 8
    },
    {
        "r_name": "Room #606",
        "r_id": 606,
        "stud_count": 10
    },
    {
        "r_name": "Room #607",
        "r_id": 607,
        "stud_count": 11
    },
    {
        "r_name": "Room #608",
        "r_id": 608,
        "stud_count": 14
    },
    {
        "r_name": "Room #609",
        "r_id": 609,
        "stud_count": 10
    },
    {
        "r_name": "Room #61",
        "r_id": 61,
        "stud_count": 11
    },
    {
        "r_name": "Room #610",
        "r_id": 610,
        "stud_count": 8
    },
    {
        "r_name": "Room #611",
        "r_id": 611,
        "stud_count": 4
    },
    {
        "r_name": "Room #612",
        "r_id": 612,
        "stud_count": 10
    },
    {
        "r_name": "Room #613",
        "r_id": 613,
        "stud_count": 11
    },
    {
        "r_name": "Room #614",
        "r_id": 614,
        "stud_count": 6
    },
    {
        "r_name": "Room #615",
        "r_id": 615,
        "stud_count": 7
    },
    {
        "r_name": "Room #616",
        "r_id": 616,
        "stud_count": 7
    },
    {
        "r_name": "Room #617",
        "r_id": 617,
        "stud_count": 10
    },
    {
        "r_name": "Room #618",
        "r_id": 618,
        "stud_count": 12
    },
    {
        "r_name": "Room #619",
        "r_id": 619,
        "stud_count": 9
    },
    {
        "r_name": "Room #62",
        "r_id": 62,
        "stud_count": 14
    },
    {
        "r_name": "Room #620",
        "r_id": 620,
        "stud_count": 10
    },
    {
        "r_name": "Room #621",
        "r_id": 621,
        "stud_count": 10
    },
    {
        "r_name": "Room #622",
        "r_id": 622,
        "stud_count": 13
    },
    {
        "r_name": "Room #623",
        "r_id": 623,
        "stud_count": 10
    },
    {
        "r_name": "Room #624",
        "r_id": 624,
        "stud_count": 8
    },
    {
        "r_name": "Room #625",
        "r_id": 625,
        "stud_count": 10
    },
    {
        "r_name": "Room #626",
        "r_id": 626,
        "stud_count": 13
    },
    {
        "r_name": "Room #627",
        "r_id": 627,
        "stud_count": 15
    },
    {
        "r_name": "Room #628",
        "r_id": 628,
        "stud_count": 5
    },
    {
        "r_name": "Room #629",
        "r_id": 629,
        "stud_count": 12
    },
    {
        "r_name": "Room #63",
        "r_id": 63,
        "stud_count": 9
    },
    {
        "r_name": "Room #630",
        "r_id": 630,
        "stud_count": 10
    },
    {
        "r_name": "Room #631",
        "r_id": 631,
        "stud_count": 16
    },
    {
        "r_name": "Room #632",
        "r_id": 632,
        "stud_count": 9
    },
    {
        "r_name": "Room #633",
        "r_id": 633,
        "stud_count": 7
    },
    {
        "r_name": "Room #634",
        "r_id": 634,
        "stud_count": 6
    },
    {
        "r_name": "Room #635",
        "r_id": 635,
        "stud_count": 8
    },
    {
        "r_name": "Room #636",
        "r_id": 636,
        "stud_count": 5
    },
    {
        "r_name": "Room #637",
        "r_id": 637,
        "stud_count": 13
    },
    {
        "r_name": "Room #638",
        "r_id": 638,
        "stud_count": 7
    },
    {
        "r_name": "Room #639",
        "r_id": 639,
        "stud_count": 8
    },
    {
        "r_name": "Room #64",
        "r_id": 64,
        "stud_count": 11
    },
    {
        "r_name": "Room #640",
        "r_id": 640,
        "stud_count": 6
    },
    {
        "r_name": "Room #641",
        "r_id": 641,
        "stud_count": 8
    },
    {
        "r_name": "Room #642",
        "r_id": 642,
        "stud_count": 9
    },
    {
        "r_name": "Room #643",
        "r_id": 643,
        "stud_count": 11
    },
    {
        "r_name": "Room #644",
        "r_id": 644,
        "stud_count": 8
    },
    {
        "r_name": "Room #645",
        "r_id": 645,
        "stud_count": 6
    },
    {
        "r_name": "Room #646",
        "r_id": 646,
        "stud_count": 14
    },
    {
        "r_name": "Room #647",
        "r_id": 647,
        "stud_count": 9
    },
    {
        "r_name": "Room #648",
        "r_id": 648,
        "stud_count": 8
    },
    {
        "r_name": "Room #649",
        "r_id": 649,
        "stud_count": 9
    },
    {
        "r_name": "Room #65",
        "r_id": 65,
        "stud_count": 16
    },
    {
        "r_name": "Room #650",
        "r_id": 650,
        "stud_count": 10
    },
    {
        "r_name": "Room #651",
        "r_id": 651,
        "stud_count": 10
    },
    {
        "r_name": "Room #652",
        "r_id": 652,
        "stud_count": 7
    },
    {
        "r_name": "Room #653",
        "r_id": 653,
        "stud_count": 8
    },
    {
        "r_name": "Room #654",
        "r_id": 654,
        "stud_count": 12
    },
    {
        "r_name": "Room #655",
        "r_id": 655,
        "stud_count": 9
    },
    {
        "r_name": "Room #656",
        "r_id": 656,
        "stud_count": 13
    },
    {
        "r_name": "Room #657",
        "r_id": 657,
        "stud_count": 15
    },
    {
        "r_name": "Room #658",
        "r_id": 658,
        "stud_count": 10
    },
    {
        "r_name": "Room #659",
        "r_id": 659,
        "stud_count": 7
    },
    {
        "r_name": "Room #66",
        "r_id": 66,
        "stud_count": 6
    },
    {
        "r_name": "Room #660",
        "r_id": 660,
        "stud_count": 13
    },
    {
        "r_name": "Room #661",
        "r_id": 661,
        "stud_count": 3
    },
    {
        "r_name": "Room #662",
        "r_id": 662,
        "stud_count": 7
    },
    {
        "r_name": "Room #663",
        "r_id": 663,
        "stud_count": 6
    },
    {
        "r_name": "Room #664",
        "r_id": 664,
        "stud_count": 5
    },
    {
        "r_name": "Room #665",
        "r_id": 665,
        "stud_count": 14
    },
    {
        "r_name": "Room #666",
        "r_id": 666,
        "stud_count": 8
    },
    {
        "r_name": "Room #667",
        "r_id": 667,
        "stud_count": 8
    },
    {
        "r_name": "Room #668",
        "r_id": 668,
        "stud_count": 8
    },
    {
        "r_name": "Room #669",
        "r_id": 669,
        "stud_count": 7
    },
    {
        "r_name": "Room #67",
        "r_id": 67,
        "stud_count": 10
    },
    {
        "r_name": "Room #670",
        "r_id": 670,
        "stud_count": 10
    },
    {
        "r_name": "Room #671",
        "r_id": 671,
        "stud_count": 9
    },
    {
        "r_name": "Room #672",
        "r_id": 672,
        "stud_count": 10
    },
    {
        "r_name": "Room #673",
        "r_id": 673,
        "stud_count": 9
    },
    {
        "r_name": "Room #674",
        "r_id": 674,
        "stud_count": 9
    },
    {
        "r_name": "Room #675",
        "r_id": 675,
        "stud_count": 12
    },
    {
        "r_name": "Room #676",
        "r_id": 676,
        "stud_count": 8
    },
    {
        "r_name": "Room #677",
        "r_id": 677,
        "stud_count": 3
    },
    {
        "r_name": "Room #678",
        "r_id": 678,
        "stud_count": 8
    },
    {
        "r_name": "Room #679",
        "r_id": 679,
        "stud_count": 14
    },
    {
        "r_name": "Room #68",
        "r_id": 68,
        "stud_count": 12
    },
    {
        "r_name": "Room #680",
        "r_id": 680,
        "stud_count": 10
    },
    {
        "r_name": "Room #681",
        "r_id": 681,
        "stud_count": 4
    },
    {
        "r_name": "Room #682",
        "r_id": 682,
        "stud_count": 11
    },
    {
        "r_name": "Room #683",
        "r_id": 683,
        "stud_count": 9
    },
    {
        "r_name": "Room #684",
        "r_id": 684,
        "stud_count": 10
    },
    {
        "r_name": "Room #685",
        "r_id": 685,
        "stud_count": 12
    },
    {
        "r_name": "Room #686",
        "r_id": 686,
        "stud_count": 7
    },
    {
        "r_name": "Room #687",
        "r_id": 687,
        "stud_count": 8
    },
    {
        "r_name": "Room #688",
        "r_id": 688,
        "stud_count": 10
    },
    {
        "r_name": "Room #689",
        "r_id": 689,
        "stud_count": 7
    },
    {
        "r_name": "Room #69",
        "r_id": 69,
        "stud_count": 12
    },
    {
        "r_name": "Room #690",
        "r_id": 690,
        "stud_count": 9
    },
    {
        "r_name": "Room #691",
        "r_id": 691,
        "stud_count": 8
    },
    {
        "r_name": "Room #692",
        "r_id": 692,
        "stud_count": 10
    },
    {
        "r_name": "Room #693",
        "r_id": 693,
        "stud_count": 10
    },
    {
        "r_name": "Room #694",
        "r_id": 694,
        "stud_count": 7
    },
    {
        "r_name": "Room #695",
        "r_id": 695,
        "stud_count": 15
    },
    {
        "r_name": "Room #696",
        "r_id": 696,
        "stud_count": 9
    },
    {
        "r_name": "Room #697",
        "r_id": 697,
        "stud_count": 9
    },
    {
        "r_name": "Room #698",
        "r_id": 698,
        "stud_count": 5
    },
    {
        "r_name": "Room #699",
        "r_id": 699,
        "stud_count": 15
    },
    {
        "r_name": "Room #7",
        "r_id": 7,
        "stud_count": 10
    },
    {
        "r_name": "Room #70",
        "r_id": 70,
        "stud_count": 12
    },
    {
        "r_name": "Room #700",
        "r_id": 700,
        "stud_count": 7
    },
    {
        "r_name": "Room #701",
        "r_id": 701,
        "stud_count": 11
    },
    {
        "r_name": "Room #702",
        "r_id": 702,
        "stud_count": 11
    },
    {
        "r_name": "Room #703",
        "r_id": 703,
        "stud_count": 12
    },
    {
        "r_name": "Room #704",
        "r_id": 704,
        "stud_count": 8
    },
    {
        "r_name": "Room #705",
        "r_id": 705,
        "stud_count": 9
    },
    {
        "r_name": "Room #706",
        "r_id": 706,
        "stud_count": 9
    },
    {
        "r_name": "Room #707",
        "r_id": 707,
        "stud_count": 9
    },
    {
        "r_name": "Room #708",
        "r_id": 708,
        "stud_count": 11
    },
    {
        "r_name": "Room #709",
        "r_id": 709,
        "stud_count": 14
    },
    {
        "r_name": "Room #71",
        "r_id": 71,
        "stud_count": 10
    },
    {
        "r_name": "Room #710",
        "r_id": 710,
        "stud_count": 4
    },
    {
        "r_name": "Room #711",
        "r_id": 711,
        "stud_count": 12
    },
    {
        "r_name": "Room #712",
        "r_id": 712,
        "stud_count": 8
    },
    {
        "r_name": "Room #713",
        "r_id": 713,
        "stud_count": 12
    },
    {
        "r_name": "Room #714",
        "r_id": 714,
        "stud_count": 16
    },
    {
        "r_name": "Room #715",
        "r_id": 715,
        "stud_count": 5
    },
    {
        "r_name": "Room #716",
        "r_id": 716,
        "stud_count": 14
    },
    {
        "r_name": "Room #717",
        "r_id": 717,
        "stud_count": 11
    },
    {
        "r_name": "Room #718",
        "r_id": 718,
        "stud_count": 8
    },
    {
        "r_name": "Room #719",
        "r_id": 719,
        "stud_count": 14
    },
    {
        "r_name": "Room #72",
        "r_id": 72,
        "stud_count": 8
    },
    {
        "r_name": "Room #720",
        "r_id": 720,
        "stud_count": 9
    },
    {
        "r_name": "Room #721",
        "r_id": 721,
        "stud_count": 7
    },
    {
        "r_name": "Room #722",
        "r_id": 722,
        "stud_count": 9
    },
    {
        "r_name": "Room #723",
        "r_id": 723,
        "stud_count": 7
    },
    {
        "r_name": "Room #724",
        "r_id": 724,
        "stud_count": 12
    },
    {
        "r_name": "Room #725",
        "r_id": 725,
        "stud_count": 14
    },
    {
        "r_name": "Room #726",
        "r_id": 726,
        "stud_count": 6
    },
    {
        "r_name": "Room #727",
        "r_id": 727,
        "stud_count": 8
    },
    {
        "r_name": "Room #728",
        "r_id": 728,
        "stud_count": 11
    },
    {
        "r_name": "Room #729",
        "r_id": 729,
        "stud_count": 12
    },
    {
        "r_name": "Room #73",
        "r_id": 73,
        "stud_count": 20
    },
    {
        "r_name": "Room #730",
        "r_id": 730,
        "stud_count": 14
    },
    {
        "r_name": "Room #731",
        "r_id": 731,
        "stud_count": 19
    },
    {
        "r_name": "Room #732",
        "r_id": 732,
        "stud_count": 6
    },
    {
        "r_name": "Room #733",
        "r_id": 733,
        "stud_count": 14
    },
    {
        "r_name": "Room #734",
        "r_id": 734,
        "stud_count": 12
    },
    {
        "r_name": "Room #735",
        "r_id": 735,
        "stud_count": 8
    },
    {
        "r_name": "Room #736",
        "r_id": 736,
        "stud_count": 9
    },
    {
        "r_name": "Room #737",
        "r_id": 737,
        "stud_count": 13
    },
    {
        "r_name": "Room #738",
        "r_id": 738,
        "stud_count": 12
    },
    {
        "r_name": "Room #739",
        "r_id": 739,
        "stud_count": 9
    },
    {
        "r_name": "Room #74",
        "r_id": 74,
        "stud_count": 17
    },
    {
        "r_name": "Room #740",
        "r_id": 740,
        "stud_count": 14
    },
    {
        "r_name": "Room #741",
        "r_id": 741,
        "stud_count": 13
    },
    {
        "r_name": "Room #742",
        "r_id": 742,
        "stud_count": 10
    },
    {
        "r_name": "Room #743",
        "r_id": 743,
        "stud_count": 12
    },
    {
        "r_name": "Room #744",
        "r_id": 744,
        "stud_count": 6
    },
    {
        "r_name": "Room #745",
        "r_id": 745,
        "stud_count": 9
    },
    {
        "r_name": "Room #746",
        "r_id": 746,
        "stud_count": 9
    },
    {
        "r_name": "Room #747",
        "r_id": 747,
        "stud_count": 13
    },
    {
        "r_name": "Room #748",
        "r_id": 748,
        "stud_count": 9
    },
    {
        "r_name": "Room #749",
        "r_id": 749,
        "stud_count": 13
    },
    {
        "r_name": "Room #75",
        "r_id": 75,
        "stud_count": 7
    },
    {
        "r_name": "Room #750",
        "r_id": 750,
        "stud_count": 11
    },
    {
        "r_name": "Room #751",
        "r_id": 751,
        "stud_count": 12
    },
    {
        "r_name": "Room #752",
        "r_id": 752,
        "stud_count": 12
    },
    {
        "r_name": "Room #753",
        "r_id": 753,
        "stud_count": 8
    },
    {
        "r_name": "Room #754",
        "r_id": 754,
        "stud_count": 5
    },
    {
        "r_name": "Room #755",
        "r_id": 755,
        "stud_count": 12
    },
    {
        "r_name": "Room #756",
        "r_id": 756,
        "stud_count": 12
    },
    {
        "r_name": "Room #757",
        "r_id": 757,
        "stud_count": 9
    },
    {
        "r_name": "Room #758",
        "r_id": 758,
        "stud_count": 13
    },
    {
        "r_name": "Room #759",
        "r_id": 759,
        "stud_count": 15
    },
    {
        "r_name": "Room #76",
        "r_id": 76,
        "stud_count": 6
    },
    {
        "r_name": "Room #760",
        "r_id": 760,
        "stud_count": 8
    },
    {
        "r_name": "Room #761",
        "r_id": 761,
        "stud_count": 9
    },
    {
        "r_name": "Room #762",
        "r_id": 762,
        "stud_count": 11
    },
    {
        "r_name": "Room #763",
        "r_id": 763,
        "stud_count": 7
    },
    {
        "r_name": "Room #764",
        "r_id": 764,
        "stud_count": 9
    },
    {
        "r_name": "Room #765",
        "r_id": 765,
        "stud_count": 8
    },
    {
        "r_name": "Room #766",
        "r_id": 766,
        "stud_count": 15
    },
    {
        "r_name": "Room #767",
        "r_id": 767,
        "stud_count": 11
    },
    {
        "r_name": "Room #768",
        "r_id": 768,
        "stud_count": 11
    },
    {
        "r_name": "Room #769",
        "r_id": 769,
        "stud_count": 10
    },
    {
        "r_name": "Room #77",
        "r_id": 77,
        "stud_count": 9
    },
    {
        "r_name": "Room #770",
        "r_id": 770,
        "stud_count": 9
    },
    {
        "r_name": "Room #771",
        "r_id": 771,
        "stud_count": 14
    },
    {
        "r_name": "Room #772",
        "r_id": 772,
        "stud_count": 5
    },
    {
        "r_name": "Room #773",
        "r_id": 773,
        "stud_count": 11
    },
    {
        "r_name": "Room #774",
        "r_id": 774,
        "stud_count": 8
    },
    {
        "r_name": "Room #775",
        "r_id": 775,
        "stud_count": 9
    },
    {
        "r_name": "Room #776",
        "r_id": 776,
        "stud_count": 7
    },
    {
        "r_name": "Room #777",
        "r_id": 777,
        "stud_count": 5
    },
    {
        "r_name": "Room #778",
        "r_id": 778,
        "stud_count": 13
    },
    {
        "r_name": "Room #779",
        "r_id": 779,
        "stud_count": 13
    },
    {
        "r_name": "Room #78",
        "r_id": 78,
        "stud_count": 8
    },
    {
        "r_name": "Room #780",
        "r_id": 780,
        "stud_count": 9
    },
    {
        "r_name": "Room #781",
        "r_id": 781,
        "stud_count": 13
    },
    {
        "r_name": "Room #782",
        "r_id": 782,
        "stud_count": 8
    },
    {
        "r_name": "Room #783",
        "r_id": 783,
        "stud_count": 8
    },
    {
        "r_name": "Room #784",
        "r_id": 784,
        "stud_count": 12
    },
    {
        "r_name": "Room #785",
        "r_id": 785,
        "stud_count": 10
    },
    {
        "r_name": "Room #786",
        "r_id": 786,
        "stud_count": 12
    },
    {
        "r_name": "Room #787",
        "r_id": 787,
        "stud_count": 8
    },
    {
        "r_name": "Room #788",
        "r_id": 788,
        "stud_count": 5
    },
    {
        "r_name": "Room #789",
        "r_id": 789,
        "stud_count": 10
    },
    {
        "r_name": "Room #79",
        "r_id": 79,
        "stud_count": 6
    },
    {
        "r_name": "Room #790",
        "r_id": 790,
        "stud_count": 8
    },
    {
        "r_name": "Room #791",
        "r_id": 791,
        "stud_count": 10
    },
    {
        "r_name": "Room #792",
        "r_id": 792,
        "stud_count": 7
    },
    {
        "r_name": "Room #793",
        "r_id": 793,
        "stud_count": 15
    },
    {
        "r_name": "Room #794",
        "r_id": 794,
        "stud_count": 5
    },
    {
        "r_name": "Room #795",
        "r_id": 795,
        "stud_count": 12
    },
    {
        "r_name": "Room #796",
        "r_id": 796,
        "stud_count": 8
    },
    {
        "r_name": "Room #797",
        "r_id": 797,
        "stud_count": 11
    },
    {
        "r_name": "Room #798",
        "r_id": 798,
        "stud_count": 5
    },
    {
        "r_name": "Room #799",
        "r_id": 799,
        "stud_count": 13
    },
    {
        "r_name": "Room #8",
        "r_id": 8,
        "stud_count": 12
    },
    {
        "r_name": "Room #80",
        "r_id": 80,
        "stud_count": 7
    },
    {
        "r_name": "Room #800",
        "r_id": 800,
        "stud_count": 5
    },
    {
        "r_name": "Room #801",
        "r_id": 801,
        "stud_count": 10
    },
    {
        "r_name": "Room #802",
        "r_id": 802,
        "stud_count": 12
    },
    {
        "r_name": "Room #803",
        "r_id": 803,
        "stud_count": 11
    },
    {
        "r_name": "Room #804",
        "r_id": 804,
        "stud_count": 6
    },
    {
        "r_name": "Room #805",
        "r_id": 805,
        "stud_count": 10
    },
    {
        "r_name": "Room #806",
        "r_id": 806,
        "stud_count": 12
    },
    {
        "r_name": "Room #807",
        "r_id": 807,
        "stud_count": 9
    },
    {
        "r_name": "Room #808",
        "r_id": 808,
        "stud_count": 11
    },
    {
        "r_name": "Room #809",
        "r_id": 809,
        "stud_count": 13
    },
    {
        "r_name": "Room #81",
        "r_id": 81,
        "stud_count": 12
    },
    {
        "r_name": "Room #810",
        "r_id": 810,
        "stud_count": 2
    },
    {
        "r_name": "Room #811",
        "r_id": 811,
        "stud_count": 5
    },
    {
        "r_name": "Room #812",
        "r_id": 812,
        "stud_count": 7
    },
    {
        "r_name": "Room #813",
        "r_id": 813,
        "stud_count": 20
    },
    {
        "r_name": "Room #814",
        "r_id": 814,
        "stud_count": 10
    },
    {
        "r_name": "Room #815",
        "r_id": 815,
        "stud_count": 9
    },
    {
        "r_name": "Room #816",
        "r_id": 816,
        "stud_count": 10
    },
    {
        "r_name": "Room #817",
        "r_id": 817,
        "stud_count": 12
    },
    {
        "r_name": "Room #818",
        "r_id": 818,
        "stud_count": 12
    },
    {
        "r_name": "Room #819",
        "r_id": 819,
        "stud_count": 9
    },
    {
        "r_name": "Room #82",
        "r_id": 82,
        "stud_count": 15
    },
    {
        "r_name": "Room #820",
        "r_id": 820,
        "stud_count": 13
    },
    {
        "r_name": "Room #821",
        "r_id": 821,
        "stud_count": 11
    },
    {
        "r_name": "Room #822",
        "r_id": 822,
        "stud_count": 10
    },
    {
        "r_name": "Room #823",
        "r_id": 823,
        "stud_count": 7
    },
    {
        "r_name": "Room #824",
        "r_id": 824,
        "stud_count": 9
    },
    {
        "r_name": "Room #825",
        "r_id": 825,
        "stud_count": 11
    },
    {
        "r_name": "Room #826",
        "r_id": 826,
        "stud_count": 9
    },
    {
        "r_name": "Room #827",
        "r_id": 827,
        "stud_count": 7
    },
    {
        "r_name": "Room #828",
        "r_id": 828,
        "stud_count": 10
    },
    {
        "r_name": "Room #829",
        "r_id": 829,
        "stud_count": 12
    },
    {
        "r_name": "Room #83",
        "r_id": 83,
        "stud_count": 11
    },
    {
        "r_name": "Room #830",
        "r_id": 830,
        "stud_count": 8
    },
    {
        "r_name": "Room #831",
        "r_id": 831,
        "stud_count": 6
    },
    {
        "r_name": "Room #832",
        "r_id": 832,
        "stud_count": 14
    },
    {
        "r_name": "Room #833",
        "r_id": 833,
        "stud_count": 9
    },
    {
        "r_name": "Room #834",
        "r_id": 834,
        "stud_count": 10
    },
    {
        "r_name": "Room #835",
        "r_id": 835,
        "stud_count": 16
    },
    {
        "r_name": "Room #836",
        "r_id": 836,
        "stud_count": 14
    },
    {
        "r_name": "Room #837",
        "r_id": 837,
        "stud_count": 11
    },
    {
        "r_name": "Room #838",
        "r_id": 838,
        "stud_count": 14
    },
    {
        "r_name": "Room #839",
        "r_id": 839,
        "stud_count": 9
    },
    {
        "r_name": "Room #84",
        "r_id": 84,
        "stud_count": 11
    },
    {
        "r_name": "Room #840",
        "r_id": 840,
        "stud_count": 8
    },
    {
        "r_name": "Room #841",
        "r_id": 841,
        "stud_count": 6
    },
    {
        "r_name": "Room #842",
        "r_id": 842,
        "stud_count": 6
    },
    {
        "r_name": "Room #843",
        "r_id": 843,
        "stud_count": 12
    },
    {
        "r_name": "Room #844",
        "r_id": 844,
        "stud_count": 11
    },
    {
        "r_name": "Room #845",
        "r_id": 845,
        "stud_count": 11
    },
    {
        "r_name": "Room #846",
        "r_id": 846,
        "stud_count": 11
    },
    {
        "r_name": "Room #847",
        "r_id": 847,
        "stud_count": 16
    },
    {
        "r_name": "Room #848",
        "r_id": 848,
        "stud_count": 14
    },
    {
        "r_name": "Room #849",
        "r_id": 849,
        "stud_count": 9
    },
    {
        "r_name": "Room #85",
        "r_id": 85,
        "stud_count": 6
    },
    {
        "r_name": "Room #850",
        "r_id": 850,
        "stud_count": 12
    },
    {
        "r_name": "Room #851",
        "r_id": 851,
        "stud_count": 6
    },
    {
        "r_name": "Room #852",
        "r_id": 852,
        "stud_count": 10
    },
    {
        "r_name": "Room #853",
        "r_id": 853,
        "stud_count": 8
    },
    {
        "r_name": "Room #854",
        "r_id": 854,
        "stud_count": 13
    },
    {
        "r_name": "Room #855",
        "r_id": 855,
        "stud_count": 12
    },
    {
        "r_name": "Room #856",
        "r_id": 856,
        "stud_count": 10
    },
    {
        "r_name": "Room #857",
        "r_id": 857,
        "stud_count": 6
    },
    {
        "r_name": "Room #858",
        "r_id": 858,
        "stud_count": 9
    },
    {
        "r_name": "Room #859",
        "r_id": 859,
        "stud_count": 9
    },
    {
        "r_name": "Room #86",
        "r_id": 86,
        "stud_count": 9
    },
    {
        "r_name": "Room #860",
        "r_id": 860,
        "stud_count": 19
    },
    {
        "r_name": "Room #861",
        "r_id": 861,
        "stud_count": 9
    },
    {
        "r_name": "Room #862",
        "r_id": 862,
        "stud_count": 6
    },
    {
        "r_name": "Room #863",
        "r_id": 863,
        "stud_count": 15
    },
    {
        "r_name": "Room #864",
        "r_id": 864,
        "stud_count": 6
    },
    {
        "r_name": "Room #865",
        "r_id": 865,
        "stud_count": 12
    },
    {
        "r_name": "Room #866",
        "r_id": 866,
        "stud_count": 12
    },
    {
        "r_name": "Room #867",
        "r_id": 867,
        "stud_count": 11
    },
    {
        "r_name": "Room #868",
        "r_id": 868,
        "stud_count": 9
    },
    {
        "r_name": "Room #869",
        "r_id": 869,
        "stud_count": 9
    },
    {
        "r_name": "Room #87",
        "r_id": 87,
        "stud_count": 13
    },
    {
        "r_name": "Room #870",
        "r_id": 870,
        "stud_count": 6
    },
    {
        "r_name": "Room #871",
        "r_id": 871,
        "stud_count": 10
    },
    {
        "r_name": "Room #872",
        "r_id": 872,
        "stud_count": 13
    },
    {
        "r_name": "Room #873",
        "r_id": 873,
        "stud_count": 4
    },
    {
        "r_name": "Room #874",
        "r_id": 874,
        "stud_count": 6
    },
    {
        "r_name": "Room #875",
        "r_id": 875,
        "stud_count": 14
    },
    {
        "r_name": "Room #876",
        "r_id": 876,
        "stud_count": 6
    },
    {
        "r_name": "Room #877",
        "r_id": 877,
        "stud_count": 11
    },
    {
        "r_name": "Room #878",
        "r_id": 878,
        "stud_count": 11
    },
    {
        "r_name": "Room #879",
        "r_id": 879,
        "stud_count": 15
    },
    {
        "r_name": "Room #88",
        "r_id": 88,
        "stud_count": 9
    },
    {
        "r_name": "Room #880",
        "r_id": 880,
        "stud_count": 9
    },
    {
        "r_name": "Room #881",
        "r_id": 881,
        "stud_count": 11
    },
    {
        "r_name": "Room #882",
        "r_id": 882,
        "stud_count": 7
    },
    {
        "r_name": "Room #883",
        "r_id": 883,
        "stud_count": 9
    },
    {
        "r_name": "Room #884",
        "r_id": 884,
        "stud_count": 14
    },
    {
        "r_name": "Room #885",
        "r_id": 885,
        "stud_count": 7
    },
    {
        "r_name": "Room #886",
        "r_id": 886,
        "stud_count": 6
    },
    {
        "r_name": "Room #887",
        "r_id": 887,
        "stud_count": 7
    },
    {
        "r_name": "Room #888",
        "r_id": 888,
        "stud_count": 11
    },
    {
        "r_name": "Room #889",
        "r_id": 889,
        "stud_count": 8
    },
    {
        "r_name": "Room #89",
        "r_id": 89,
        "stud_count": 7
    },
    {
        "r_name": "Room #890",
        "r_id": 890,
        "stud_count": 8
    },
    {
        "r_name": "Room #891",
        "r_id": 891,
        "stud_count": 11
    },
    {
        "r_name": "Room #892",
        "r_id": 892,
        "stud_count": 10
    },
    {
        "r_name": "Room #893",
        "r_id": 893,
        "stud_count": 13
    },
    {
        "r_name": "Room #894",
        "r_id": 894,
        "stud_count": 17
    },
    {
        "r_name": "Room #895",
        "r_id": 895,
        "stud_count": 6
    },
    {
        "r_name": "Room #896",
        "r_id": 896,
        "stud_count": 8
    },
    {
        "r_name": "Room #897",
        "r_id": 897,
        "stud_count": 9
    },
    {
        "r_name": "Room #898",
        "r_id": 898,
        "stud_count": 12
    },
    {
        "r_name": "Room #899",
        "r_id": 899,
        "stud_count": 10
    },
    {
        "r_name": "Room #9",
        "r_id": 9,
        "stud_count": 7
    },
    {
        "r_name": "Room #90",
        "r_id": 90,
        "stud_count": 11
    },
    {
        "r_name": "Room #900",
        "r_id": 900,
        "stud_count": 11
    },
    {
        "r_name": "Room #901",
        "r_id": 901,
        "stud_count": 8
    },
    {
        "r_name": "Room #902",
        "r_id": 902,
        "stud_count": 5
    },
    {
        "r_name": "Room #903",
        "r_id": 903,
        "stud_count": 11
    },
    {
        "r_name": "Room #904",
        "r_id": 904,
        "stud_count": 8
    },
    {
        "r_name": "Room #905",
        "r_id": 905,
        "stud_count": 19
    },
    {
        "r_name": "Room #906",
        "r_id": 906,
        "stud_count": 10
    },
    {
        "r_name": "Room #907",
        "r_id": 907,
        "stud_count": 12
    },
    {
        "r_name": "Room #908",
        "r_id": 908,
        "stud_count": 7
    },
    {
        "r_name": "Room #909",
        "r_id": 909,
        "stud_count": 12
    },
    {
        "r_name": "Room #91",
        "r_id": 91,
        "stud_count": 10
    },
    {
        "r_name": "Room #910",
        "r_id": 910,
        "stud_count": 10
    },
    {
        "r_name": "Room #911",
        "r_id": 911,
        "stud_count": 10
    },
    {
        "r_name": "Room #912",
        "r_id": 912,
        "stud_count": 13
    },
    {
        "r_name": "Room #913",
        "r_id": 913,
        "stud_count": 3
    },
    {
        "r_name": "Room #914",
        "r_id": 914,
        "stud_count": 13
    },
    {
        "r_name": "Room #915",
        "r_id": 915,
        "stud_count": 5
    },
    {
        "r_name": "Room #916",
        "r_id": 916,
        "stud_count": 8
    },
    {
        "r_name": "Room #917",
        "r_id": 917,
        "stud_count": 9
    },
    {
        "r_name": "Room #918",
        "r_id": 918,
        "stud_count": 14
    },
    {
        "r_name": "Room #919",
        "r_id": 919,
        "stud_count": 5
    },
    {
        "r_name": "Room #92",
        "r_id": 92,
        "stud_count": 5
    },
    {
        "r_name": "Room #920",
        "r_id": 920,
        "stud_count": 8
    },
    {
        "r_name": "Room #921",
        "r_id": 921,
        "stud_count": 10
    },
    {
        "r_name": "Room #922",
        "r_id": 922,
        "stud_count": 10
    },
    {
        "r_name": "Room #923",
        "r_id": 923,
        "stud_count": 9
    },
    {
        "r_name": "Room #924",
        "r_id": 924,
        "stud_count": 12
    },
    {
        "r_name": "Room #925",
        "r_id": 925,
        "stud_count": 8
    },
    {
        "r_name": "Room #926",
        "r_id": 926,
        "stud_count": 14
    },
    {
        "r_name": "Room #927",
        "r_id": 927,
        "stud_count": 9
    },
    {
        "r_name": "Room #928",
        "r_id": 928,
        "stud_count": 8
    },
    {
        "r_name": "Room #929",
        "r_id": 929,
        "stud_count": 9
    },
    {
        "r_name": "Room #93",
        "r_id": 93,
        "stud_count": 12
    },
    {
        "r_name": "Room #930",
        "r_id": 930,
        "stud_count": 15
    },
    {
        "r_name": "Room #931",
        "r_id": 931,
        "stud_count": 7
    },
    {
        "r_name": "Room #932",
        "r_id": 932,
        "stud_count": 9
    },
    {
        "r_name": "Room #933",
        "r_id": 933,
        "stud_count": 10
    },
    {
        "r_name": "Room #934",
        "r_id": 934,
        "stud_count": 4
    },
    {
        "r_name": "Room #935",
        "r_id": 935,
        "stud_count": 10
    },
    {
        "r_name": "Room #936",
        "r_id": 936,
        "stud_count": 13
    },
    {
        "r_name": "Room #937",
        "r_id": 937,
        "stud_count": 11
    },
    {
        "r_name": "Room #938",
        "r_id": 938,
        "stud_count": 12
    },
    {
        "r_name": "Room #939",
        "r_id": 939,
        "stud_count": 9
    },
    {
        "r_name": "Room #94",
        "r_id": 94,
        "stud_count": 11
    },
    {
        "r_name": "Room #940",
        "r_id": 940,
        "stud_count": 7
    },
    {
        "r_name": "Room #941",
        "r_id": 941,
        "stud_count": 11
    },
    {
        "r_name": "Room #942",
        "r_id": 942,
        "stud_count": 11
    },
    {
        "r_name": "Room #943",
        "r_id": 943,
        "stud_count": 5
    },
    {
        "r_name": "Room #944",
        "r_id": 944,
        "stud_count": 8
    },
    {
        "r_name": "Room #945",
        "r_id": 945,
        "stud_count": 10
    },
    {
        "r_name": "Room #946",
        "r_id": 946,
        "stud_count": 11
    },
    {
        "r_name": "Room #947",
        "r_id": 947,
        "stud_count": 8
    },
    {
        "r_name": "Room #948",
        "r_id": 948,
        "stud_count": 13
    },
    {
        "r_name": "Room #949",
        "r_id": 949,
        "stud_count": 10
    },
    {
        "r_name": "Room #95",
        "r_id": 95,
        "stud_count": 8
    },
    {
        "r_name": "Room #950",
        "r_id": 950,
        "stud_count": 12
    },
    {
        "r_name": "Room #951",
        "r_id": 951,
        "stud_count": 8
    },
    {
        "r_name": "Room #952",
        "r_id": 952,
        "stud_count": 13
    },
    {
        "r_name": "Room #953",
        "r_id": 953,
        "stud_count": 11
    },
    {
        "r_name": "Room #954",
        "r_id": 954,
        "stud_count": 7
    },
    {
        "r_name": "Room #955",
        "r_id": 955,
        "stud_count": 13
    },
    {
        "r_name": "Room #956",
        "r_id": 956,
        "stud_count": 6
    },
    {
        "r_name": "Room #957",
        "r_id": 957,
        "stud_count": 9
    },
    {
        "r_name": "Room #958",
        "r_id": 958,
        "stud_count": 14
    },
    {
        "r_name": "Room #959",
        "r_id": 959,
        "stud_count": 8
    },
    {
        "r_name": "Room #96",
        "r_id": 96,
        "stud_count": 9
    },
    {
        "r_name": "Room #960",
        "r_id": 960,
        "stud_count": 8
    },
    {
        "r_name": "Room #961",
        "r_id": 961,
        "stud_count": 17
    },
    {
        "r_name": "Room #962",
        "r_id": 962,
        "stud_count": 9
    },
    {
        "r_name": "Room #963",
        "r_id": 963,
        "stud_count": 6
    },
    {
        "r_name": "Room #964",
        "r_id": 964,
        "stud_count": 5
    },
    {
        "r_name": "Room #965",
        "r_id": 965,
        "stud_count": 15
    },
    {
        "r_name": "Room #966",
        "r_id": 966,
        "stud_count": 11
    },
    {
        "r_name": "Room #967",
        "r_id": 967,
        "stud_count": 11
    },
    {
        "r_name": "Room #968",
        "r_id": 968,
        "stud_count": 17
    },
    {
        "r_name": "Room #969",
        "r_id": 969,
        "stud_count": 16
    },
    {
        "r_name": "Room #97",
        "r_id": 97,
        "stud_count": 5
    },
    {
        "r_name": "Room #970",
        "r_id": 970,
        "stud_count": 6
    },
    {
        "r_name": "Room #971",
        "r_id": 971,
        "stud_count": 9
    },
    {
        "r_name": "Room #972",
        "r_id": 972,
        "stud_count": 4
    },
    {
        "r_name": "Room #973",
        "r_id": 973,
        "stud_count": 9
    },
    {
        "r_name": "Room #974",
        "r_id": 974,
        "stud_count": 8
    },
    {
        "r_name": "Room #975",
        "r_id": 975,
        "stud_count": 9
    },
    {
        "r_name": "Room #976",
        "r_id": 976,
        "stud_count": 7
    },
    {
        "r_name": "Room #977",
        "r_id": 977,
        "stud_count": 10
    },
    {
        "r_name": "Room #978",
        "r_id": 978,
        "stud_count": 12
    },
    {
        "r_name": "Room #979",
        "r_id": 979,
        "stud_count": 10
    },
    {
        "r_name": "Room #98",
        "r_id": 98,
        "stud_count": 11
    },
    {
        "r_name": "Room #980",
        "r_id": 980,
        "stud_count": 14
    },
    {
        "r_name": "Room #981",
        "r_id": 981,
        "stud_count": 12
    },
    {
        "r_name": "Room #982",
        "r_id": 982,
        "stud_count": 8
    },
    {
        "r_name": "Room #983",
        "r_id": 983,
        "stud_count": 6
    },
    {
        "r_name": "Room #984",
        "r_id": 984,
        "stud_count": 13
    },
    {
        "r_name": "Room #985",
        "r_id": 985,
        "stud_count": 3
    },
    {
        "r_name": "Room #986",
        "r_id": 986,
        "stud_count": 13
    },
    {
        "r_name": "Room #987",
        "r_id": 987,
        "stud_count": 7
    },
    {
        "r_name": "Room #988",
        "r_id": 988,
        "stud_count": 10
    },
    {
        "r_name": "Room #989",
        "r_id": 989,
        "stud_count": 10
    },
    {
        "r_name": "Room #99",
        "r_id": 99,
        "stud_count": 8
    },
    {
        "r_name": "Room #990",
        "r_id": 990,
        "stud_count": 5
    },
    {
        "r_name": "Room #991",
        "r_id": 991,
        "stud_count": 9
    },
    {
        "r_name": "Room #992",
        "r_id": 992,
        "stud_count": 13
    },
    {
        "r_name": "Room #993",
        "r_id": 993,
        "stud_count": 10
    },
    {
        "r_name": "Room #994",
        "r_id": 994,
        "stud_count": 6
    },
    {
        "r_name": "Room #995",
        "r_id": 995,
        "stud_count": 13
    },
    {
        "r_name": "Room #996",
        "r_id": 996,
        "stud_count": 8
    },
    {
        "r_name": "Room #997",
        "r_id": 997,
        "stud_count": 9
    },
    {
        "r_name": "Room #998",
        "r_id": 998,
        "stud_count": 14
    },
    {
        "r_name": "Room #999",
        "r_id": 999,
        "stud_count": 12
    }
]